lo3-0.3.1a0.dist-info/METADATA
lo3-0.3.1a0.dist-info/WHEEL
lo3/__init__.py
lo3/lo3.cpython-312-darwin.so
lo3-0.3.1a0.dist-info/RECORD
