Metadata-Version: 2.3
Name: lo3
Version: 0.3.1a0
Classifier: Programming Language :: Rust
Classifier: Programming Language :: Python :: Implementation :: CPython
Classifier: Programming Language :: Python :: Implementation :: PyPy
Summary: Faster logger than python native logging package. 
License: MIT
Requires-Python: >=3.8
Project-URL: Source Code, https://github.com/DataEnggNerd/MH370
